Metadata-Version: 2.1
Name: statist
Version: 0.0.5
Summary: Get Todoist user stats in CLI
Home-page: https://yoginth.com
Author: Yoginth
Author-email: yoginth@protonmail.com
License: UNKNOWN
Project-URL: Source, https://gitlab.com/yo/statist
Platform: UNKNOWN
Classifier: Programming Language :: Python
Classifier: Natural Language :: English
Classifier: Environment :: Console
Classifier: Operating System :: OS Independent
Classifier: Intended Audience :: End Users/Desktop
Classifier: License :: OSI Approved :: MIT License
